tests/cases/05_full_cache_coverage_plan/manual/manual_hypothesis_probe.sv
`timescale 1ns/1ps
`default_nettype none

module manual_hypothesis_probe (
  input  wire        clock,
  input  wire        reset,

  input  wire        miss_start,
  input  wire        flush,
  input  wire        mem_resp_valid,
  output reg         outstanding_valid,
  output reg         miss_cancelled,
  output reg         cpu_resp_valid,
  output reg         line_allocated_after_flush,

  input  wire        fill_old_line,
  input  wire        write_full_line,
  input  wire        conflict_access,
  output reg         dirty,
  output reg         writeback_valid,
  output reg         refill_valid,

  input  wire        init_word,
  input  wire        partial_write,
  input  wire [31:0] partial_wdata,
  input  wire [3:0]  partial_wmask,
  output reg  [31:0] partial_word
);
  reg [31:0] memory_word;
  reg        line_valid;

  always @(posedge clock) begin
    if (reset) begin
      outstanding_valid <= 1'b0;
      miss_cancelled <= 1'b0;
      cpu_resp_valid <= 1'b0;
      line_allocated_after_flush <= 1'b0;
      line_valid <= 1'b0;
      dirty <= 1'b0;
      writeback_valid <= 1'b0;
      refill_valid <= 1'b0;
      memory_word <= 32'h4433_2211;
      partial_word <= 32'h4433_2211;
    end else begin
      cpu_resp_valid <= 1'b0;
      writeback_valid <= 1'b0;
      refill_valid <= 1'b0;

      if (miss_start) begin
        outstanding_valid <= 1'b1;
        miss_cancelled <= 1'b0;
        line_allocated_after_flush <= 1'b0;
      end

      if (flush && outstanding_valid) begin
        miss_cancelled <= 1'b1;
      end

      if (mem_resp_valid && outstanding_valid) begin
        outstanding_valid <= 1'b0;
        if (miss_cancelled) begin
          line_allocated_after_flush <= 1'b0;
          cpu_resp_valid <= 1'b0;
        end else begin
          line_allocated_after_flush <= 1'b1;
          cpu_resp_valid <= 1'b1;
        end
      end

      if (fill_old_line) begin
        line_valid <= 1'b1;
        dirty <= 1'b0;
      end

      if (write_full_line && line_valid) begin
        dirty <= 1'b1;
        memory_word <= 32'hDDCC_BBAA;
      end

      if (conflict_access && line_valid) begin
        if (dirty) begin
          writeback_valid <= 1'b1;
        end
        refill_valid <= 1'b1;
        dirty <= 1'b0;
      end

      if (init_word) begin
        partial_word <= 32'h4433_2211;
      end

      if (partial_write) begin
        if (partial_wmask[0]) partial_word[7:0] <= partial_wdata[7:0];
        if (partial_wmask[1]) partial_word[15:8] <= partial_wdata[15:8];
        if (partial_wmask[2]) partial_word[23:16] <= partial_wdata[23:16];
        if (partial_wmask[3]) partial_word[31:24] <= partial_wdata[31:24];
      end
    end
  end
endmodule

`default_nettype wire

tests/cases/05_full_cache_coverage_plan/manual/manual_hypothesis_probe_tb.sv
`timescale 1ns/1ps
`default_nettype none

module manual_hypothesis_probe_tb;
  reg clock = 1'b0;
  reg reset = 1'b1;

  reg miss_start = 1'b0;
  reg flush = 1'b0;
  reg mem_resp_valid = 1'b0;
  wire outstanding_valid;
  wire miss_cancelled;
  wire cpu_resp_valid;
  wire line_allocated_after_flush;

  reg fill_old_line = 1'b0;
  reg write_full_line = 1'b0;
  reg conflict_access = 1'b0;
  wire dirty;
  wire writeback_valid;
  wire refill_valid;

  reg init_word = 1'b0;
  reg partial_write = 1'b0;
  reg [31:0] partial_wdata = 32'h0000_0000;
  reg [3:0] partial_wmask = 4'b0000;
  wire [31:0] partial_word;

  integer cycle = 0;
  integer pass_count = 0;
  reg saw_writeback_before_refill = 1'b0;
  reg saw_writeback = 1'b0;

  manual_hypothesis_probe dut (
    .clock(clock),
    .reset(reset),
    .miss_start(miss_start),
    .flush(flush),
    .mem_resp_valid(mem_resp_valid),
    .outstanding_valid(outstanding_valid),
    .miss_cancelled(miss_cancelled),
    .cpu_resp_valid(cpu_resp_valid),
    .line_allocated_after_flush(line_allocated_after_flush),
    .fill_old_line(fill_old_line),
    .write_full_line(write_full_line),
    .conflict_access(conflict_access),
    .dirty(dirty),
    .writeback_valid(writeback_valid),
    .refill_valid(refill_valid),
    .init_word(init_word),
    .partial_write(partial_write),
    .partial_wdata(partial_wdata),
    .partial_wmask(partial_wmask),
    .partial_word(partial_word)
  );

  always #5 clock = ~clock;

  always @(posedge clock) begin
    cycle <= cycle + 1;
    $display(
      "C%0d phase flush_miss out=%0b cancelled=%0b cpu_resp=%0b alloc_after_flush=%0b dirty_evict dirty=%0b wb=%0b refill=%0b partial_word=%h",
      cycle,
      outstanding_valid,
      miss_cancelled,
      cpu_resp_valid,
      line_allocated_after_flush,
      dirty,
      writeback_valid,
      refill_valid,
      partial_word
    );
  end

  task automatic pulse(input integer selector);
    begin
      @(negedge clock);
      if (selector == 0) miss_start <= 1'b1;
      if (selector == 1) flush <= 1'b1;
      if (selector == 2) mem_resp_valid <= 1'b1;
      if (selector == 3) fill_old_line <= 1'b1;
      if (selector == 4) write_full_line <= 1'b1;
      if (selector == 5) conflict_access <= 1'b1;
      if (selector == 6) init_word <= 1'b1;
      if (selector == 7) partial_write <= 1'b1;
      @(negedge clock);
      miss_start <= 1'b0;
      flush <= 1'b0;
      mem_resp_valid <= 1'b0;
      fill_old_line <= 1'b0;
      write_full_line <= 1'b0;
      conflict_access <= 1'b0;
      init_word <= 1'b0;
      partial_write <= 1'b0;
    end
  endtask

  initial begin
    $dumpfile("reports/artifacts/05_full_cache_coverage_plan/manual_hypothesis_probe.vcd");
    $dumpvars(0, manual_hypothesis_probe_tb);

    repeat (4) @(posedge clock);
    reset <= 1'b0;
    repeat (2) @(posedge clock);

    $display("MANUAL_EVENT: HYP_FLUSH_OUTSTANDING_MISS start");
    pulse(0);
    pulse(1);
    pulse(2);
    @(posedge clock);
    if (!cpu_resp_valid && !line_allocated_after_flush && !outstanding_valid) begin
      pass_count = pass_count + 1;
      $display("MANUAL_PASS: HYP_FLUSH_OUTSTANDING_MISS not reproduced; cancelled response was dropped");
    end else begin
      $display("MANUAL_FAIL: HYP_FLUSH_OUTSTANDING_MISS reproduced");
    end

    repeat (2) @(posedge clock);
    $display("MANUAL_EVENT: HYP_DIRTY_EVICTION_ORDER start");
    pulse(3);
    pulse(4);
    @(posedge clock);
    pulse(5);
    @(posedge clock);
    if (writeback_valid) begin
      saw_writeback = 1'b1;
    end
    if (writeback_valid && refill_valid) begin
      saw_writeback_before_refill = 1'b1;
    end
    @(posedge clock);
    if (saw_writeback && saw_writeback_before_refill) begin
      pass_count = pass_count + 1;
      $display("MANUAL_PASS: HYP_DIRTY_EVICTION_ORDER not reproduced; writeback is visible with replacement refill");
    end else begin
      $display("MANUAL_FAIL: HYP_DIRTY_EVICTION_ORDER reproduced");
    end

    repeat (2) @(posedge clock);
    $display("MANUAL_EVENT: HYP_PARTIAL_MASK_MERGE start");
    pulse(6);
    @(negedge clock);
    partial_wdata <= 32'hDDCC_BBAA;
    partial_wmask <= 4'b0101;
    partial_write <= 1'b1;
    @(negedge clock);
    partial_write <= 1'b0;
    partial_wmask <= 4'b0000;
    @(posedge clock);
    if (partial_word == 32'h44CC_22AA) begin
      pass_count = pass_count + 1;
      $display("MANUAL_PASS: HYP_PARTIAL_MASK_MERGE not reproduced; untouched lanes are preserved");
    end else begin
      $display("MANUAL_FAIL: HYP_PARTIAL_MASK_MERGE reproduced word=%h", partial_word);
    end

    repeat (5) @(posedge clock);
    if (pass_count == 3) begin
      $display("MANUAL_RESULT: THREE_UCAGENT_HYPOTHESES_NOT_REPRODUCED_IN_VERILOG_WAVEFORM");
    end else begin
      $display("MANUAL_RESULT: MANUAL_VERILOG_FOUND_FAILURE pass_count=%0d", pass_count);
    end
    $finish;
  end
endmodule

`default_nettype wire

reports/artifacts/05_full_cache_coverage_plan/manual_hypothesis_probe.vcd
$date
	Sun Jun 28 20:48:15 2026
$end
$version
	Icarus Verilog
$end
$timescale
	1ps
$end
$scope module manual_hypothesis_probe_tb $end
$var wire 1 ! writeback_valid $end
$var wire 1 " refill_valid $end
$var wire 32 # partial_word [31:0] $end
$var wire 1 $ outstanding_valid $end
$var wire 1 % miss_cancelled $end
$var wire 1 & line_allocated_after_flush $end
$var wire 1 ' dirty $end
$var wire 1 ( cpu_resp_valid $end
$var reg 1 ) clock $end
$var reg 1 * conflict_access $end
$var reg 1 + fill_old_line $end
$var reg 1 , flush $end
$var reg 1 - init_word $end
$var reg 1 . mem_resp_valid $end
$var reg 1 / miss_start $end
$var reg 32 0 partial_wdata [31:0] $end
$var reg 4 1 partial_wmask [3:0] $end
$var reg 1 2 partial_write $end
$var reg 1 3 reset $end
$var reg 1 4 saw_writeback $end
$var reg 1 5 saw_writeback_before_refill $end
$var reg 1 6 write_full_line $end
$var integer 32 7 cycle [31:0] $end
$var integer 32 8 pass_count [31:0] $end
$scope module dut $end
$var wire 1 ) clock $end
$var wire 1 * conflict_access $end
$var wire 1 + fill_old_line $end
$var wire 1 , flush $end
$var wire 1 - init_word $end
$var wire 1 . mem_resp_valid $end
$var wire 1 / miss_start $end
$var wire 32 9 partial_wdata [31:0] $end
$var wire 4 : partial_wmask [3:0] $end
$var wire 1 2 partial_write $end
$var wire 1 3 reset $end
$var wire 1 6 write_full_line $end
$var reg 1 ( cpu_resp_valid $end
$var reg 1 ' dirty $end
$var reg 1 & line_allocated_after_flush $end
$var reg 1 ; line_valid $end
$var reg 32 < memory_word [31:0] $end
$var reg 1 % miss_cancelled $end
$var reg 1 $ outstanding_valid $end
$var reg 32 = partial_word [31:0] $end
$var reg 1 " refill_valid $end
$var reg 1 ! writeback_valid $end
$upscope $end
$scope task pulse $end
$upscope $end
$upscope $end
$enddefinitions $end
$comment Show the parameter values. $end
$dumpall
$end
#0
$dumpvars
bx =
bx <
x;
b0 :
b0 9
b0 8
b0 7
06
05
04
13
02
b0 1
b0 0
0/
0.
0-
0,
0+
0*
0)
x(
x'
x&
x%
x$
bx #
x"
x!
$end
#5000
b1000100001100110010001000010001 #
b1000100001100110010001000010001 =
b1000100001100110010001000010001 <
0"
0!
0'
0;
0&
0(
0%
0$
b1 7
1)
#10000
0)
#15000
b10 7
1)
#20000
0)
#25000
b11 7
1)
#30000
0)
#35000
03
b100 7
1)
#40000
0)
#45000
b101 7
1)
#50000
0)
#55000
b110 7
1)
#60000
1/
0)
#65000
1$
b111 7
1)
#70000
0/
0)
#75000
b1000 7
1)
#80000
1,
0)
#85000
1%
b1001 7
1)
#90000
0,
0)
#95000
b1010 7
1)
#100000
1.
0)
#105000
0$
b1011 7
1)
#110000
0.
0)
#115000
b1100 7
b1 8
1)
#120000
0)
#125000
b1101 7
1)
#130000
0)
#135000
b1110 7
1)
#140000
1+
0)
#145000
1;
b1111 7
1)
#150000
0+
0)
#155000
b10000 7
1)
#160000
16
0)
#165000
b11011101110011001011101110101010 <
1'
b10001 7
1)
#170000
06
0)
#175000
b10010 7
1)
#180000
1*
0)
#185000
0'
1"
1!
b10011 7
1)
#190000
0*
0)
#195000
b10100 7
0"
0!
15
14
1)
#200000
0)
#205000
b10101 7
b10 8
1)
#210000
0)
#215000
b10110 7
1)
#220000
0)
#225000
b10111 7
1)
#230000
1-
0)
#235000
b11000 7
1)
#240000
0-
0)
#245000
b11001 7
1)
#250000
12
b101 1
b101 :
b11011101110011001011101110101010 0
b11011101110011001011101110101010 9
0)
#255000
b11010 7
b1000100110011000010001010101010 #
b1000100110011000010001010101010 =
1)
#260000
b0 1
b0 :
02
0)
#265000
b11011 7
b11 8
1)
#270000
0)
#275000
b11100 7
1)
#280000
0)
#285000
b11101 7
1)
#290000
0)
#295000
b11110 7
1)
#300000
0)
#305000
b11111 7
1)
#310000
0)
#315000
b100000 7
1)
